fosslight_binary/__init__.py
fosslight_binary/_binary.py
fosslight_binary/_binary_dao.py
fosslight_binary/_help.py
fosslight_binary/_jar_analysis.py
fosslight_binary/_simple_mode.py
fosslight_binary/binary_analysis.py
fosslight_binary/cli.py
fosslight_binary/LICENSES/LICENSE
fosslight_binary/LICENSES/LicenseRef-3rd_party_licenses.txt
fosslight_binary/third_party/dependency-check/LICENSE.txt
fosslight_binary/third_party/dependency-check/NOTICE.txt
fosslight_binary/third_party/dependency-check/README.md
fosslight_binary/third_party/dependency-check/bin/completion-for-dependency-check.sh
fosslight_binary/third_party/dependency-check/bin/dependency-check.bat
fosslight_binary/third_party/dependency-check/bin/dependency-check.sh
fosslight_binary/third_party/dependency-check/lib/aho-corasick-double-array-trie-1.2.3.jar
fosslight_binary/third_party/dependency-check/lib/android-json-0.0.20131108.vaadin1.jar
fosslight_binary/third_party/dependency-check/lib/annotations-26.0.2-1.jar
fosslight_binary/third_party/dependency-check/lib/ant-1.10.15.jar
fosslight_binary/third_party/dependency-check/lib/bcpg-jdk18on-1.78.jar
fosslight_binary/third_party/dependency-check/lib/bcprov-jdk18on-1.78.jar
fosslight_binary/third_party/dependency-check/lib/commons-cli-1.10.0.jar
fosslight_binary/third_party/dependency-check/lib/commons-codec-1.19.0.jar
fosslight_binary/third_party/dependency-check/lib/commons-collections-3.2.2.jar
fosslight_binary/third_party/dependency-check/lib/commons-collections4-4.5.0.jar
fosslight_binary/third_party/dependency-check/lib/commons-compress-1.27.1.jar
fosslight_binary/third_party/dependency-check/lib/commons-dbcp2-2.13.0.jar
fosslight_binary/third_party/dependency-check/lib/commons-digester-2.1.jar
fosslight_binary/third_party/dependency-check/lib/commons-io-2.20.0.jar
fosslight_binary/third_party/dependency-check/lib/commons-jcs3-core-3.2.1.jar
fosslight_binary/third_party/dependency-check/lib/commons-lang3-3.19.0.jar
fosslight_binary-5.1.12.dist-info/licenses/LICENSE
fosslight_binary-5.1.12.dist-info/licenses/LICENSES/Apache-2.0.txt
fosslight_binary-5.1.12.dist-info/licenses/LICENSES/LicenseRef-3rd_party_licenses.txt
fosslight_binary-5.1.12.dist-info/METADATA
fosslight_binary-5.1.12.dist-info/WHEEL
fosslight_binary-5.1.12.dist-info/entry_points.txt
fosslight_binary-5.1.12.dist-info/top_level.txt
fosslight_binary-5.1.12.dist-info/RECORD
