Metadata-Version: 2.4
Name: fosslight_binary
Version: 5.1.12
Summary: FOSSLight Binary Scanner
Home-page: https://github.com/fosslight/fosslight_binary_scanner
Download-URL: https://github.com/fosslight/fosslight_binary_scanner
Author: LG Electronics
License: Apache-2.0
Classifier: License :: OSI Approved :: Apache Software License
Classifier: Programming Language :: Python :: 3
Classifier: Programming Language :: Python :: 3.10
Classifier: Programming Language :: Python :: 3.11
Classifier: Programming Language :: Python :: 3.12
Requires-Python: >=3.10,<3.13
License-File: LICENSE
License-File: LICENSES/Apache-2.0.txt
License-File: LICENSES/LicenseRef-3rd_party_licenses.txt
Requires-Dist: binaryornot
Requires-Dist: numpy
Requires-Dist: pandas
Requires-Dist: parmap
Requires-Dist: psycopg2-binary
Requires-Dist: python-dateutil
Requires-Dist: py-tlsh
Requires-Dist: pytz
Requires-Dist: XlsxWriter
Requires-Dist: PyYAML
Requires-Dist: fosslight_util>=2.1.13
Requires-Dist: python-magic-bin; sys_platform == "win32"
Requires-Dist: python-magic; "darwin" in sys_platform
Requires-Dist: python-magic; "linux" in sys_platform
Dynamic: author
Dynamic: classifier
Dynamic: description
Dynamic: description-content-type
Dynamic: download-url
Dynamic: home-page
Dynamic: license
Dynamic: license-file
Dynamic: provides-extra
Dynamic: requires-dist
Dynamic: requires-python
Dynamic: summary
